cy_ioc_finder_v2/__init__.py
cy_ioc_finder_v2/utility.py
cy_ioc_finder_v2/ioc_finder/__init__.py
cy_ioc_finder_v2/ioc_finder/data.py
cy_ioc_finder_v2/ioc_finder/ioc_finder.py
cy_ioc_finder_v2/ioc_finder/ioc_grammars.py
cy_ioc_finder-7.2.13.dist-info/METADATA
cy_ioc_finder-7.2.13.dist-info/WHEEL
cy_ioc_finder-7.2.13.dist-info/entry_points.txt
cy_ioc_finder-7.2.13.dist-info/top_level.txt
cy_ioc_finder-7.2.13.dist-info/zip-safe
cy_ioc_finder-7.2.13.dist-info/RECORD
